__init__.py
cart.py
develop.py
models.py
py.typed
store.py
support.py
texture.py
chartout-0.0.0.dist-info/METADATA
chartout-0.0.0.dist-info/WHEEL
chartout-0.0.0.dist-info/top_level.txt
chartout-0.0.0.dist-info/RECORD
