Metadata-Version: 2.4
Name: chartout
Version: 0.0.0
Summary: Chartout - Print Your Insights, Anytime, Anywhere
Home-page: https://chartout.io
Download-URL: https://download_url.com
Author: mattijn
Author-email: info@hoekinsights.nl
License: GPL-3.0 license
Project-URL: Source, https://github.com/hoekinsights/chartout
Keywords: python3 python reserve reserver reserved
Classifier: Development Status :: 1 - Planning
Classifier: Programming Language :: Python :: 3.6
Classifier: Programming Language :: Python :: 3.7
Classifier: Programming Language :: Python :: 3.8
Classifier: Programming Language :: Python :: 3.9
Classifier: Programming Language :: Python :: 3.10
Classifier: Programming Language :: Python :: 3.11
Classifier: Programming Language :: Python :: 3.12
Requires-Python: >=3.6
Dynamic: author
Dynamic: author-email
Dynamic: classifier
Dynamic: description
Dynamic: description-content-type
Dynamic: download-url
Dynamic: home-page
Dynamic: keywords
Dynamic: license
Dynamic: project-url
Dynamic: requires-python
Dynamic: summary
